ures/__init__.py
ures/data_structure/__init__.py
ures/data_structure/bi_directional_links.py
ures/data_structure/tree.py
ures/docker/__init__.py
ures/docker/cleanup.py
ures/docker/conf.py
ures/docker/container.py
ures/docker/containers.py
ures/docker/image.py
ures/docker/runtime.py
ures/files.py
ures/literature/__init__.py
ures/literature/citation/README.md
ures/literature/citation/__init__.py
ures/literature/citation/extractors.py
ures/literature/citation/manager.py
ures/literature/citation/middlewares.py
ures/literature/citation/rules/__init__.py
ures/literature/citation/rules/acm.py
ures/literature/citation/rules/basic.py
ures/literature/citation/rules/data_type.py
ures/literature/search/README.md
ures/literature/search/__init__.py
ures/literature/search/adapters.py
ures/literature/search/paper.py
ures/literature/search/search.py
ures/literature/search_cli.py
ures/markdown/__init__.py
ures/markdown/manipulator.py
ures/markdown/zettelkasten.py
ures/memory/__init__.py
ures/memory/allocator.py
ures/memory/blocks.py
ures/memory/smoke_test.py
ures/network.py
ures/secrets.py
ures/string.py
ures/timedate.py
ures/tools/__init__.py
ures/tools/decorator.py
ures/tools/enum.py
ures-2.3.1.dist-info/LICENSE
ures-2.3.1.dist-info/METADATA
ures-2.3.1.dist-info/WHEEL
ures-2.3.1.dist-info/RECORD
