Metadata-Version: 2.3
Name: ures
Version: 2.3.1
Summary: The project is designed to provide standard utilization functions for improving the reusability of frequently used functions.
License: MIT
Keywords: utilization,Research Tool,Python
Author: stone
Author-email: github@stone-bo.com
Requires-Python: >=3.11,<4.0
Classifier: Development Status :: 1 - Planning
Classifier: Intended Audience :: Developers
Classifier: License :: OSI Approved :: MIT License
Classifier: Programming Language :: Python :: 3
Classifier: Programming Language :: Python :: 3.11
Classifier: Programming Language :: Python :: 3.12
Classifier: Programming Language :: Python :: 3.13
Classifier: Programming Language :: Python :: Implementation :: PyPy
Classifier: Topic :: Software Development :: Libraries :: Python Modules
Classifier: Topic :: Utilities
Requires-Dist: beautifulsoup4 (>=4.13.4,<5.0.0)
Requires-Dist: bibtexparser (>=2.0.0b8,<3.0.0)
Requires-Dist: docker (>=7.1.0,<8.0.0)
Requires-Dist: onepassword-sdk (>=0.3.1,<0.4.0)
Requires-Dist: pycountry (>=24.6.1,<25.0.0)
Requires-Dist: pydantic (>=2.10.6,<3.0.0)
Requires-Dist: pyperclip (>=1.9.0,<2.0.0)
Requires-Dist: python-frontmatter (>=1.1.0,<2.0.0)
Requires-Dist: requests (>=2.32.5,<3.0.0)
Requires-Dist: sortedcontainers (>=2.4.0,<3.0.0)
Requires-Dist: tqdm (>=4.67.1,<5.0.0)
Requires-Dist: unidecode (>=1.4.0,<2.0.0)
Project-URL: Repository, https://github.com/stone-home/Python-URes
